{
  "version": "6",
  "dialect": "sqlite",
  "id": "f7867569-c055-4c16-b759-28b1b7601e25",
  "prevId": "00000000-0000-0000-0000-000000000000",
  "tables": {
    "images": {
      "name": "images",
      "columns": {
        "id": {
          "name": "id",
          "type": "text",
          "primaryKey": true,
          "notNull": true,
          "autoincrement": false
        },
        "url": {
          "name": "url",
          "type": "text",
          "primaryKey": false,
          "notNull": true,
          "autoincrement": false
        }
      },
      "indexes": {},
      "foreignKeys": {},
      "compositePrimaryKeys": {},
      "uniqueConstraints": {}
    }
  },
  "enums": {},
  "_meta": {
    "schemas": {},
    "tables": {},
    "columns": {}
  }
}